CHANGES.txt
MANIFEST.in
README.txt
pyzaa.py
setup.py
pyzaa.egg-info/PKG-INFO
pyzaa.egg-info/SOURCES.txt
pyzaa.egg-info/dependency_links.txt
pyzaa.egg-info/not-zip-safe
pyzaa.egg-info/top_level.txt