Metadata-Version: 1.1
Name: pyzaa
Version: 0.1.0
Summary: Python ZIP Application Archiver
Home-page: http://bitbucket.org/dholth/pyzaa/
Author: Daniel Holth
Author-email: dholth@gmail.com
License: MIT
Keywords: pyzaa
Platform: UNKNOWN
Classifier: Programming Language :: Python
Classifier: Programming Language :: Python :: 2
Classifier: Programming Language :: Python :: 2.7
Classifier: Programming Language :: Python :: 3
Classifier: Programming Language :: Python :: 3.3
